{"frames": {

"angler_animation0001":
{
	"frame": {"x":1403,"y":1311,"w":101,"h":96},
	"rotated": false,
	"trimmed": true,
	"spriteSourceSize": {"x":5,"y":1,"w":101,"h":96},
	"sourceSize": {"w":106,"h":97},
	"pivot": {"x":0.5,"y":0.5}
},
"angler_animation0002":
{
	"frame": {"x":1403,"y":1409,"w":101,"h":96},
	"rotated": false,
	"trimmed": true,
	"spriteSourceSize": {"x":4,"y":1,"w":101,"h":96},
	"sourceSize": {"w":106,"h":97},
	"pivot": {"x":0.5,"y":0.5}
},
"angler_animation0003":
{
	"frame": {"x":214,"y":1660,"w":100,"h":96},
	"rotated": true,
	"trimmed": true,
	"spriteSourceSize": {"x":4,"y":1,"w":100,"h":96},
	"sourceSize": {"w":106,"h":97},
	"pivot": {"x":0.5,"y":0.5}
},
"angler_animation0004":
{
	"frame": {"x":297,"y":1506,"w":100,"h":96},
	"rotated": true,
	"trimmed": true,
	"spriteSourceSize": {"x":4,"y":1,"w":100,"h":96},
	"sourceSize": {"w":106,"h":97},
	"pivot": {"x":0.5,"y":0.5}
},
"angler_animation0005":
{
	"frame": {"x":493,"y":1538,"w":99,"h":96},
	"rotated": true,
	"trimmed": true,
	"spriteSourceSize": {"x":4,"y":1,"w":99,"h":96},
	"sourceSize": {"w":106,"h":97},
	"pivot": {"x":0.5,"y":0.5}
},
"angler_animation0006":
{
	"frame": {"x":591,"y":1506,"w":99,"h":96},
	"rotated": true,
	"trimmed": true,
	"spriteSourceSize": {"x":4,"y":1,"w":99,"h":96},
	"sourceSize": {"w":106,"h":97},
	"pivot": {"x":0.5,"y":0.5}
},
"angler_animation0007":
{
	"frame": {"x":689,"y":1506,"w":98,"h":96},
	"rotated": false,
	"trimmed": true,
	"spriteSourceSize": {"x":4,"y":1,"w":98,"h":96},
	"sourceSize": {"w":106,"h":97},
	"pivot": {"x":0.5,"y":0.5}
},
"angler_animation0008":
{
	"frame": {"x":689,"y":1604,"w":98,"h":96},
	"rotated": false,
	"trimmed": true,
	"spriteSourceSize": {"x":4,"y":1,"w":98,"h":96},
	"sourceSize": {"w":106,"h":97},
	"pivot": {"x":0.5,"y":0.5}
},
"angler_animation0009":
{
	"frame": {"x":771,"y":1888,"w":97,"h":96},
	"rotated": true,
	"trimmed": true,
	"spriteSourceSize": {"x":4,"y":1,"w":97,"h":96},
	"sourceSize": {"w":106,"h":97},
	"pivot": {"x":0.5,"y":0.5}
},
"angler_animation0010":
{
	"frame": {"x":592,"y":1706,"w":96,"h":95},
	"rotated": true,
	"trimmed": true,
	"spriteSourceSize": {"x":4,"y":2,"w":96,"h":95},
	"sourceSize": {"w":106,"h":97},
	"pivot": {"x":0.5,"y":0.5}
},
"angler_animation0011":
{
	"frame": {"x":592,"y":1607,"w":97,"h":95},
	"rotated": true,
	"trimmed": true,
	"spriteSourceSize": {"x":4,"y":2,"w":97,"h":95},
	"sourceSize": {"w":106,"h":97},
	"pivot": {"x":0.5,"y":0.5}
},
"angler_animation0012":
{
	"frame": {"x":869,"y":1888,"w":97,"h":96},
	"rotated": true,
	"trimmed": true,
	"spriteSourceSize": {"x":4,"y":1,"w":97,"h":96},
	"sourceSize": {"w":106,"h":97},
	"pivot": {"x":0.5,"y":0.5}
},
"angler_animation0013":
{
	"frame": {"x":689,"y":1702,"w":98,"h":96},
	"rotated": false,
	"trimmed": true,
	"spriteSourceSize": {"x":4,"y":1,"w":98,"h":96},
	"sourceSize": {"w":106,"h":97},
	"pivot": {"x":0.5,"y":0.5}
},
"angler_animation0014":
{
	"frame": {"x":574,"y":1888,"w":98,"h":96},
	"rotated": true,
	"trimmed": true,
	"spriteSourceSize": {"x":4,"y":1,"w":98,"h":96},
	"sourceSize": {"w":106,"h":97},
	"pivot": {"x":0.5,"y":0.5}
},
"angler_animation0015":
{
	"frame": {"x":476,"y":1888,"w":99,"h":96},
	"rotated": true,
	"trimmed": true,
	"spriteSourceSize": {"x":4,"y":1,"w":99,"h":96},
	"sourceSize": {"w":106,"h":97},
	"pivot": {"x":0.5,"y":0.5}
},
"angler_animation0016":
{
	"frame": {"x":198,"y":1888,"w":100,"h":96},
	"rotated": true,
	"trimmed": true,
	"spriteSourceSize": {"x":4,"y":1,"w":100,"h":96},
	"sourceSize": {"w":106,"h":97},
	"pivot": {"x":0.5,"y":0.5}
},
"angler_animation0017":
{
	"frame": {"x":312,"y":1660,"w":100,"h":96},
	"rotated": true,
	"trimmed": true,
	"spriteSourceSize": {"x":4,"y":1,"w":100,"h":96},
	"sourceSize": {"w":106,"h":97},
	"pivot": {"x":0.5,"y":0.5}
},
"angler_animation0018":
{
	"frame": {"x":100,"y":1888,"w":101,"h":96},
	"rotated": true,
	"trimmed": true,
	"spriteSourceSize": {"x":4,"y":1,"w":101,"h":96},
	"sourceSize": {"w":106,"h":97},
	"pivot": {"x":0.5,"y":0.5}
},
"angler_animation0019":
{
	"frame": {"x":395,"y":1506,"w":100,"h":96},
	"rotated": true,
	"trimmed": true,
	"spriteSourceSize": {"x":5,"y":1,"w":100,"h":96},
	"sourceSize": {"w":106,"h":97},
	"pivot": {"x":0.5,"y":0.5}
},
"angler_animation0020":
{
	"frame": {"x":1403,"y":1311,"w":101,"h":96},
	"rotated": false,
	"trimmed": true,
	"spriteSourceSize": {"x":5,"y":1,"w":101,"h":96},
	"sourceSize": {"w":106,"h":97},
	"pivot": {"x":0.5,"y":0.5}
},
"deep_sea_fish01":
{
	"frame": {"x":247,"y":922,"w":237,"h":91},
	"rotated": false,
	"trimmed": false,
	"spriteSourceSize": {"x":0,"y":0,"w":237,"h":91},
	"sourceSize": {"w":237,"h":91},
	"pivot": {"x":0.5,"y":0.5}
},
"deep_sea_fish02":
{
	"frame": {"x":1,"y":928,"w":237,"h":91},
	"rotated": false,
	"trimmed": false,
	"spriteSourceSize": {"x":0,"y":0,"w":237,"h":91},
	"sourceSize": {"w":237,"h":91},
	"pivot": {"x":0.5,"y":0.5}
},
"deep_sea_fish03":
{
	"frame": {"x":240,"y":1015,"w":237,"h":91},
	"rotated": false,
	"trimmed": false,
	"spriteSourceSize": {"x":0,"y":0,"w":237,"h":91},
	"sourceSize": {"w":237,"h":91},
	"pivot": {"x":0.5,"y":0.5}
},
"deep_sea_fish04":
{
	"frame": {"x":1,"y":1021,"w":237,"h":91},
	"rotated": false,
	"trimmed": false,
	"spriteSourceSize": {"x":0,"y":0,"w":237,"h":91},
	"sourceSize": {"w":237,"h":91},
	"pivot": {"x":0.5,"y":0.5}
},
"deep_sea_fish05":
{
	"frame": {"x":240,"y":1108,"w":237,"h":91},
	"rotated": false,
	"trimmed": false,
	"spriteSourceSize": {"x":0,"y":0,"w":237,"h":91},
	"sourceSize": {"w":237,"h":91},
	"pivot": {"x":0.5,"y":0.5}
},
"deep_sea_fish06":
{
	"frame": {"x":1,"y":1114,"w":237,"h":91},
	"rotated": false,
	"trimmed": false,
	"spriteSourceSize": {"x":0,"y":0,"w":237,"h":91},
	"sourceSize": {"w":237,"h":91},
	"pivot": {"x":0.5,"y":0.5}
},
"deep_sea_fish07":
{
	"frame": {"x":1507,"y":688,"w":237,"h":91},
	"rotated": false,
	"trimmed": false,
	"spriteSourceSize": {"x":0,"y":0,"w":237,"h":91},
	"sourceSize": {"w":237,"h":91},
	"pivot": {"x":0.5,"y":0.5}
},
"deep_sea_fish08":
{
	"frame": {"x":1507,"y":781,"w":237,"h":91},
	"rotated": false,
	"trimmed": false,
	"spriteSourceSize": {"x":0,"y":0,"w":237,"h":91},
	"sourceSize": {"w":237,"h":91},
	"pivot": {"x":0.5,"y":0.5}
},
"deep_sea_fish09":
{
	"frame": {"x":1801,"y":693,"w":237,"h":91},
	"rotated": false,
	"trimmed": false,
	"spriteSourceSize": {"x":0,"y":0,"w":237,"h":91},
	"sourceSize": {"w":237,"h":91},
	"pivot": {"x":0.5,"y":0.5}
},
"dog_fish01":
{
	"frame": {"x":1965,"y":1440,"w":82,"h":94},
	"rotated": false,
	"trimmed": true,
	"spriteSourceSize": {"x":0,"y":23,"w":82,"h":94},
	"sourceSize": {"w":97,"h":120},
	"pivot": {"x":0.5,"y":0.5}
},
"dog_fish02":
{
	"frame": {"x":1,"y":1793,"w":82,"h":93},
	"rotated": false,
	"trimmed": true,
	"spriteSourceSize": {"x":0,"y":24,"w":82,"h":93},
	"sourceSize": {"w":97,"h":120},
	"pivot": {"x":0.5,"y":0.5}
},
"dog_fish03":
{
	"frame": {"x":1328,"y":923,"w":77,"h":108},
	"rotated": false,
	"trimmed": true,
	"spriteSourceSize": {"x":0,"y":12,"w":77,"h":108},
	"sourceSize": {"w":97,"h":120},
	"pivot": {"x":0.5,"y":0.5}
},
"dog_fish04":
{
	"frame": {"x":410,"y":1660,"w":81,"h":100},
	"rotated": false,
	"trimmed": true,
	"spriteSourceSize": {"x":0,"y":20,"w":81,"h":100},
	"sourceSize": {"w":97,"h":120},
	"pivot": {"x":0.5,"y":0.5}
},
"dog_fish05":
{
	"frame": {"x":393,"y":1888,"w":81,"h":100},
	"rotated": false,
	"trimmed": true,
	"spriteSourceSize": {"x":0,"y":20,"w":81,"h":100},
	"sourceSize": {"w":97,"h":120},
	"pivot": {"x":0.5,"y":0.5}
},
"dog_fish06":
{
	"frame": {"x":1965,"y":1340,"w":82,"h":98},
	"rotated": false,
	"trimmed": true,
	"spriteSourceSize": {"x":0,"y":21,"w":82,"h":98},
	"sourceSize": {"w":97,"h":120},
	"pivot": {"x":0.5,"y":0.5}
},
"dog_fish07":
{
	"frame": {"x":493,"y":1438,"w":83,"h":98},
	"rotated": false,
	"trimmed": true,
	"spriteSourceSize": {"x":0,"y":21,"w":83,"h":98},
	"sourceSize": {"w":97,"h":120},
	"pivot": {"x":0.5,"y":0.5}
},
"dog_fish08":
{
	"frame": {"x":1631,"y":1561,"w":85,"h":94},
	"rotated": false,
	"trimmed": true,
	"spriteSourceSize": {"x":0,"y":23,"w":85,"h":94},
	"sourceSize": {"w":97,"h":120},
	"pivot": {"x":0.5,"y":0.5}
},
"dog_fish09":
{
	"frame": {"x":1629,"y":1657,"w":86,"h":94},
	"rotated": false,
	"trimmed": true,
	"spriteSourceSize": {"x":0,"y":23,"w":86,"h":94},
	"sourceSize": {"w":97,"h":120},
	"pivot": {"x":0.5,"y":0.5}
},
"dog_fish10":
{
	"frame": {"x":1961,"y":1536,"w":86,"h":108},
	"rotated": false,
	"trimmed": true,
	"spriteSourceSize": {"x":0,"y":12,"w":86,"h":108},
	"sourceSize": {"w":97,"h":120},
	"pivot": {"x":0.5,"y":0.5}
},
"dog_fish11":
{
	"frame": {"x":791,"y":1350,"w":89,"h":108},
	"rotated": false,
	"trimmed": true,
	"spriteSourceSize": {"x":0,"y":12,"w":89,"h":108},
	"sourceSize": {"w":97,"h":120},
	"pivot": {"x":0.5,"y":0.5}
},
"dog_fish12":
{
	"frame": {"x":1906,"y":1795,"w":91,"h":112},
	"rotated": true,
	"trimmed": true,
	"spriteSourceSize": {"x":0,"y":8,"w":91,"h":112},
	"sourceSize": {"w":97,"h":120},
	"pivot": {"x":0.5,"y":0.5}
},
"dog_fish13":
{
	"frame": {"x":1914,"y":1646,"w":93,"h":117},
	"rotated": true,
	"trimmed": true,
	"spriteSourceSize": {"x":0,"y":3,"w":93,"h":117},
	"sourceSize": {"w":97,"h":120},
	"pivot": {"x":0.5,"y":0.5}
},
"dog_fish14":
{
	"frame": {"x":1411,"y":552,"w":94,"h":120},
	"rotated": false,
	"trimmed": true,
	"spriteSourceSize": {"x":0,"y":0,"w":94,"h":120},
	"sourceSize": {"w":97,"h":120},
	"pivot": {"x":0.5,"y":0.5}
},
"dog_fish15":
{
	"frame": {"x":296,"y":1888,"w":95,"h":100},
	"rotated": false,
	"trimmed": true,
	"spriteSourceSize": {"x":0,"y":18,"w":95,"h":100},
	"sourceSize": {"w":97,"h":120},
	"pivot": {"x":0.5,"y":0.5}
},
"dog_fish16":
{
	"frame": {"x":199,"y":1395,"w":97,"h":103},
	"rotated": false,
	"trimmed": true,
	"spriteSourceSize": {"x":0,"y":15,"w":97,"h":103},
	"sourceSize": {"w":97,"h":120},
	"pivot": {"x":0.5,"y":0.5}
},
"dog_fish17":
{
	"frame": {"x":479,"y":1140,"w":97,"h":110},
	"rotated": true,
	"trimmed": true,
	"spriteSourceSize": {"x":0,"y":9,"w":97,"h":110},
	"sourceSize": {"w":97,"h":120},
	"pivot": {"x":0.5,"y":0.5}
},
"dog_fish18":
{
	"frame": {"x":1791,"y":1744,"w":97,"h":113},
	"rotated": true,
	"trimmed": true,
	"spriteSourceSize": {"x":0,"y":6,"w":97,"h":113},
	"sourceSize": {"w":97,"h":120},
	"pivot": {"x":0.5,"y":0.5}
},
"dog_fish19":
{
	"frame": {"x":1794,"y":1645,"w":97,"h":118},
	"rotated": true,
	"trimmed": true,
	"spriteSourceSize": {"x":0,"y":1,"w":97,"h":118},
	"sourceSize": {"w":97,"h":120},
	"pivot": {"x":0.5,"y":0.5}
},
"dog_fish20":
{
	"frame": {"x":99,"y":1506,"w":97,"h":108},
	"rotated": false,
	"trimmed": true,
	"spriteSourceSize": {"x":0,"y":12,"w":97,"h":108},
	"sourceSize": {"w":97,"h":120},
	"pivot": {"x":0.5,"y":0.5}
},
"dog_fish21":
{
	"frame": {"x":1,"y":1888,"w":97,"h":111},
	"rotated": false,
	"trimmed": true,
	"spriteSourceSize": {"x":0,"y":9,"w":97,"h":111},
	"sourceSize": {"w":97,"h":120},
	"pivot": {"x":0.5,"y":0.5}
},
"dog_fish22":
{
	"frame": {"x":1411,"y":674,"w":96,"h":94},
	"rotated": true,
	"trimmed": true,
	"spriteSourceSize": {"x":0,"y":26,"w":96,"h":94},
	"sourceSize": {"w":97,"h":120},
	"pivot": {"x":0.5,"y":0.5}
},
"dog_fish23":
{
	"frame": {"x":672,"y":1888,"w":97,"h":97},
	"rotated": false,
	"trimmed": true,
	"spriteSourceSize": {"x":0,"y":23,"w":97,"h":97},
	"sourceSize": {"w":97,"h":120},
	"pivot": {"x":0.5,"y":0.5}
},
"dog_fish24":
{
	"frame": {"x":493,"y":1660,"w":97,"h":99},
	"rotated": false,
	"trimmed": true,
	"spriteSourceSize": {"x":0,"y":21,"w":97,"h":99},
	"sourceSize": {"w":97,"h":120},
	"pivot": {"x":0.5,"y":0.5}
},
"dog_fish25":
{
	"frame": {"x":1403,"y":1212,"w":97,"h":102},
	"rotated": true,
	"trimmed": true,
	"spriteSourceSize": {"x":0,"y":18,"w":97,"h":102},
	"sourceSize": {"w":97,"h":120},
	"pivot": {"x":0.5,"y":0.5}
},
"dog_fish26":
{
	"frame": {"x":298,"y":1395,"w":97,"h":103},
	"rotated": true,
	"trimmed": true,
	"spriteSourceSize": {"x":0,"y":16,"w":97,"h":103},
	"sourceSize": {"w":97,"h":120},
	"pivot": {"x":0.5,"y":0.5}
},
"dog_fish27":
{
	"frame": {"x":198,"y":1506,"w":97,"h":108},
	"rotated": false,
	"trimmed": true,
	"spriteSourceSize": {"x":0,"y":11,"w":97,"h":108},
	"sourceSize": {"w":97,"h":120},
	"pivot": {"x":0.5,"y":0.5}
},
"dog_fish28":
{
	"frame": {"x":1,"y":1506,"w":96,"h":110},
	"rotated": false,
	"trimmed": true,
	"spriteSourceSize": {"x":0,"y":9,"w":96,"h":110},
	"sourceSize": {"w":97,"h":120},
	"pivot": {"x":0.5,"y":0.5}
},
"dog_fish29":
{
	"frame": {"x":789,"y":1660,"w":91,"h":94},
	"rotated": false,
	"trimmed": true,
	"spriteSourceSize": {"x":0,"y":25,"w":91,"h":94},
	"sourceSize": {"w":97,"h":120},
	"pivot": {"x":0.5,"y":0.5}
},
"dog_fish30":
{
	"frame": {"x":590,"y":1804,"w":82,"h":94},
	"rotated": true,
	"trimmed": true,
	"spriteSourceSize": {"x":0,"y":25,"w":82,"h":94},
	"sourceSize": {"w":97,"h":120},
	"pivot": {"x":0.5,"y":0.5}
},
"dog_fish31":
{
	"frame": {"x":686,"y":1804,"w":82,"h":94},
	"rotated": true,
	"trimmed": true,
	"spriteSourceSize": {"x":0,"y":25,"w":82,"h":94},
	"sourceSize": {"w":97,"h":120},
	"pivot": {"x":0.5,"y":0.5}
},
"dog_fish32":
{
	"frame": {"x":85,"y":1793,"w":82,"h":93},
	"rotated": false,
	"trimmed": true,
	"spriteSourceSize": {"x":0,"y":25,"w":82,"h":93},
	"sourceSize": {"w":97,"h":120},
	"pivot": {"x":0.5,"y":0.5}
},
"dog_fish33":
{
	"frame": {"x":169,"y":1793,"w":82,"h":93},
	"rotated": false,
	"trimmed": true,
	"spriteSourceSize": {"x":0,"y":25,"w":82,"h":93},
	"sourceSize": {"w":97,"h":120},
	"pivot": {"x":0.5,"y":0.5}
},
"dog_fish34":
{
	"frame": {"x":967,"y":1888,"w":82,"h":94},
	"rotated": false,
	"trimmed": true,
	"spriteSourceSize": {"x":0,"y":24,"w":82,"h":94},
	"sourceSize": {"w":97,"h":120},
	"pivot": {"x":0.5,"y":0.5}
},
"dog_fish35":
{
	"frame": {"x":1051,"y":1888,"w":82,"h":94},
	"rotated": false,
	"trimmed": true,
	"spriteSourceSize": {"x":0,"y":24,"w":82,"h":94},
	"sourceSize": {"w":97,"h":120},
	"pivot": {"x":0.5,"y":0.5}
},
"dog_fish36":
{
	"frame": {"x":1135,"y":1888,"w":82,"h":94},
	"rotated": false,
	"trimmed": true,
	"spriteSourceSize": {"x":0,"y":24,"w":82,"h":94},
	"sourceSize": {"w":97,"h":120},
	"pivot": {"x":0.5,"y":0.5}
},
"dog_fish37":
{
	"frame": {"x":253,"y":1793,"w":82,"h":93},
	"rotated": false,
	"trimmed": true,
	"spriteSourceSize": {"x":0,"y":24,"w":82,"h":93},
	"sourceSize": {"w":97,"h":120},
	"pivot": {"x":0.5,"y":0.5}
},
"dog_fish38":
{
	"frame": {"x":337,"y":1793,"w":82,"h":93},
	"rotated": false,
	"trimmed": true,
	"spriteSourceSize": {"x":0,"y":24,"w":82,"h":93},
	"sourceSize": {"w":97,"h":120},
	"pivot": {"x":0.5,"y":0.5}
},
"dog_fish39":
{
	"frame": {"x":1209,"y":1793,"w":82,"h":94},
	"rotated": true,
	"trimmed": true,
	"spriteSourceSize": {"x":0,"y":23,"w":82,"h":94},
	"sourceSize": {"w":97,"h":120},
	"pivot": {"x":0.5,"y":0.5}
},
"dog_fish40":
{
	"frame": {"x":421,"y":1793,"w":82,"h":93},
	"rotated": false,
	"trimmed": true,
	"spriteSourceSize": {"x":0,"y":24,"w":82,"h":93},
	"sourceSize": {"w":97,"h":120},
	"pivot": {"x":0.5,"y":0.5}
},
"dog_fish41":
{
	"frame": {"x":1219,"y":1888,"w":82,"h":94},
	"rotated": false,
	"trimmed": true,
	"spriteSourceSize": {"x":0,"y":23,"w":82,"h":94},
	"sourceSize": {"w":97,"h":120},
	"pivot": {"x":0.5,"y":0.5}
},
"dog_fish42":
{
	"frame": {"x":1965,"y":1440,"w":82,"h":94},
	"rotated": false,
	"trimmed": true,
	"spriteSourceSize": {"x":0,"y":23,"w":82,"h":94},
	"sourceSize": {"w":97,"h":120},
	"pivot": {"x":0.5,"y":0.5}
},
"dog_fish43":
{
	"frame": {"x":1303,"y":1888,"w":82,"h":94},
	"rotated": false,
	"trimmed": true,
	"spriteSourceSize": {"x":0,"y":23,"w":82,"h":94},
	"sourceSize": {"w":97,"h":120},
	"pivot": {"x":0.5,"y":0.5}
},
"dog_fish44":
{
	"frame": {"x":1387,"y":1719,"w":82,"h":94},
	"rotated": true,
	"trimmed": true,
	"spriteSourceSize": {"x":0,"y":23,"w":82,"h":94},
	"sourceSize": {"w":97,"h":120},
	"pivot": {"x":0.5,"y":0.5}
},
"dog_fish45":
{
	"frame": {"x":789,"y":1793,"w":82,"h":93},
	"rotated": false,
	"trimmed": true,
	"spriteSourceSize": {"x":0,"y":24,"w":82,"h":93},
	"sourceSize": {"w":97,"h":120},
	"pivot": {"x":0.5,"y":0.5}
},
"dog_fish46":
{
	"frame": {"x":1305,"y":1803,"w":82,"h":94},
	"rotated": true,
	"trimmed": true,
	"spriteSourceSize": {"x":0,"y":23,"w":82,"h":94},
	"sourceSize": {"w":97,"h":120},
	"pivot": {"x":0.5,"y":0.5}
},
"dog_fish47":
{
	"frame": {"x":873,"y":1793,"w":82,"h":93},
	"rotated": false,
	"trimmed": true,
	"spriteSourceSize": {"x":0,"y":24,"w":82,"h":93},
	"sourceSize": {"w":97,"h":120},
	"pivot": {"x":0.5,"y":0.5}
},
"dog_fish48":
{
	"frame": {"x":957,"y":1793,"w":82,"h":93},
	"rotated": false,
	"trimmed": true,
	"spriteSourceSize": {"x":0,"y":24,"w":82,"h":93},
	"sourceSize": {"w":97,"h":120},
	"pivot": {"x":0.5,"y":0.5}
},
"dog_fish49":
{
	"frame": {"x":1041,"y":1793,"w":82,"h":93},
	"rotated": false,
	"trimmed": true,
	"spriteSourceSize": {"x":0,"y":24,"w":82,"h":93},
	"sourceSize": {"w":97,"h":120},
	"pivot": {"x":0.5,"y":0.5}
},
"dog_fish50":
{
	"frame": {"x":1483,"y":1723,"w":82,"h":94},
	"rotated": true,
	"trimmed": true,
	"spriteSourceSize": {"x":0,"y":24,"w":82,"h":94},
	"sourceSize": {"w":97,"h":120},
	"pivot": {"x":0.5,"y":0.5}
},
"dog_fish51":
{
	"frame": {"x":1125,"y":1793,"w":82,"h":91},
	"rotated": false,
	"trimmed": true,
	"spriteSourceSize": {"x":0,"y":26,"w":82,"h":91},
	"sourceSize": {"w":97,"h":120},
	"pivot": {"x":0.5,"y":0.5}
},
"dog_fish52":
{
	"frame": {"x":1327,"y":1033,"w":77,"h":93},
	"rotated": false,
	"trimmed": true,
	"spriteSourceSize": {"x":1,"y":23,"w":77,"h":93},
	"sourceSize": {"w":97,"h":120},
	"pivot": {"x":0.5,"y":0.5}
},
"eel01":
{
	"frame": {"x":1087,"y":1615,"w":202,"h":67},
	"rotated": false,
	"trimmed": true,
	"spriteSourceSize": {"x":20,"y":3,"w":202,"h":67},
	"sourceSize": {"w":240,"h":75},
	"pivot": {"x":0.5,"y":0.5}
},
"eel02":
{
	"frame": {"x":1727,"y":1235,"w":206,"h":69},
	"rotated": true,
	"trimmed": true,
	"spriteSourceSize": {"x":17,"y":2,"w":206,"h":69},
	"sourceSize": {"w":240,"h":75},
	"pivot": {"x":0.5,"y":0.5}
},
"eel03":
{
	"frame": {"x":1727,"y":1021,"w":212,"h":69},
	"rotated": true,
	"trimmed": true,
	"spriteSourceSize": {"x":13,"y":3,"w":212,"h":69},
	"sourceSize": {"w":240,"h":75},
	"pivot": {"x":0.5,"y":0.5}
},
"eel04":
{
	"frame": {"x":887,"y":1125,"w":217,"h":68},
	"rotated": false,
	"trimmed": true,
	"spriteSourceSize": {"x":10,"y":3,"w":217,"h":68},
	"sourceSize": {"w":240,"h":75},
	"pivot": {"x":0.5,"y":0.5}
},
"eel05":
{
	"frame": {"x":1822,"y":306,"w":224,"h":75},
	"rotated": false,
	"trimmed": true,
	"spriteSourceSize": {"x":4,"y":0,"w":224,"h":75},
	"sourceSize": {"w":240,"h":75},
	"pivot": {"x":0.5,"y":0.5}
},
"eel06":
{
	"frame": {"x":1801,"y":786,"w":235,"h":75},
	"rotated": false,
	"trimmed": true,
	"spriteSourceSize": {"x":0,"y":0,"w":235,"h":75},
	"sourceSize": {"w":240,"h":75},
	"pivot": {"x":0.5,"y":0.5}
},
"eel07":
{
	"frame": {"x":591,"y":756,"w":240,"h":74},
	"rotated": false,
	"trimmed": true,
	"spriteSourceSize": {"x":0,"y":0,"w":240,"h":74},
	"sourceSize": {"w":240,"h":75},
	"pivot": {"x":0.5,"y":0.5}
},
"eel08":
{
	"frame": {"x":247,"y":846,"w":240,"h":74},
	"rotated": false,
	"trimmed": true,
	"spriteSourceSize": {"x":0,"y":0,"w":240,"h":74},
	"sourceSize": {"w":240,"h":75},
	"pivot": {"x":0.5,"y":0.5}
},
"eel09":
{
	"frame": {"x":1134,"y":738,"w":240,"h":74},
	"rotated": false,
	"trimmed": true,
	"spriteSourceSize": {"x":0,"y":0,"w":240,"h":74},
	"sourceSize": {"w":240,"h":75},
	"pivot": {"x":0.5,"y":0.5}
},
"eel10":
{
	"frame": {"x":888,"y":749,"w":240,"h":74},
	"rotated": false,
	"trimmed": true,
	"spriteSourceSize": {"x":0,"y":0,"w":240,"h":74},
	"sourceSize": {"w":240,"h":75},
	"pivot": {"x":0.5,"y":0.5}
},
"eel11":
{
	"frame": {"x":1507,"y":874,"w":235,"h":73},
	"rotated": false,
	"trimmed": true,
	"spriteSourceSize": {"x":0,"y":0,"w":235,"h":73},
	"sourceSize": {"w":240,"h":75},
	"pivot": {"x":0.5,"y":0.5}
},
"eel12":
{
	"frame": {"x":1801,"y":863,"w":234,"h":72},
	"rotated": false,
	"trimmed": true,
	"spriteSourceSize": {"x":0,"y":0,"w":234,"h":72},
	"sourceSize": {"w":240,"h":75},
	"pivot": {"x":0.5,"y":0.5}
},
"fugu01":
{
	"frame": {"x":555,"y":584,"w":39,"h":32},
	"rotated": false,
	"trimmed": true,
	"spriteSourceSize": {"x":22,"y":29,"w":39,"h":32},
	"sourceSize": {"w":84,"h":74},
	"pivot": {"x":0.5,"y":0.5}
},
"fugu02":
{
	"frame": {"x":555,"y":534,"w":48,"h":39},
	"rotated": true,
	"trimmed": true,
	"spriteSourceSize": {"x":18,"y":24,"w":48,"h":39},
	"sourceSize": {"w":84,"h":74},
	"pivot": {"x":0.5,"y":0.5}
},
"fugu03":
{
	"frame": {"x":70,"y":1717,"w":59,"h":52},
	"rotated": true,
	"trimmed": true,
	"spriteSourceSize": {"x":12,"y":14,"w":59,"h":52},
	"sourceSize": {"w":84,"h":74},
	"pivot": {"x":0.5,"y":0.5}
},
"fugu04":
{
	"frame": {"x":1717,"y":1703,"w":72,"h":63},
	"rotated": false,
	"trimmed": true,
	"spriteSourceSize": {"x":6,"y":7,"w":72,"h":63},
	"sourceSize": {"w":84,"h":74},
	"pivot": {"x":0.5,"y":0.5}
},
"fugu05":
{
	"frame": {"x":1317,"y":1302,"w":84,"h":74},
	"rotated": false,
	"trimmed": false,
	"spriteSourceSize": {"x":0,"y":0,"w":84,"h":74},
	"sourceSize": {"w":84,"h":74},
	"pivot": {"x":0.5,"y":0.5}
},
"fugu_fat_swimming01":
{
	"frame": {"x":811,"y":1002,"w":85,"h":74},
	"rotated": true,
	"trimmed": false,
	"spriteSourceSize": {"x":0,"y":0,"w":85,"h":74},
	"sourceSize": {"w":85,"h":74},
	"pivot": {"x":0.5,"y":0.5}
},
"fugu_fat_swimming02":
{
	"frame": {"x":1317,"y":1378,"w":84,"h":74},
	"rotated": false,
	"trimmed": true,
	"spriteSourceSize": {"x":1,"y":0,"w":84,"h":74},
	"sourceSize": {"w":85,"h":74},
	"pivot": {"x":0.5,"y":0.5}
},
"fugu_fat_swimming03":
{
	"frame": {"x":811,"y":1089,"w":85,"h":74},
	"rotated": true,
	"trimmed": false,
	"spriteSourceSize": {"x":0,"y":0,"w":85,"h":74},
	"sourceSize": {"w":85,"h":74},
	"pivot": {"x":0.5,"y":0.5}
},
"fugu_fat_swimming04":
{
	"frame": {"x":811,"y":1176,"w":85,"h":74},
	"rotated": true,
	"trimmed": false,
	"spriteSourceSize": {"x":0,"y":0,"w":85,"h":74},
	"sourceSize": {"w":85,"h":74},
	"pivot": {"x":0.5,"y":0.5}
},
"fugu_fat_swimming05":
{
	"frame": {"x":807,"y":1263,"w":85,"h":74},
	"rotated": true,
	"trimmed": false,
	"spriteSourceSize": {"x":0,"y":0,"w":85,"h":74},
	"sourceSize": {"w":85,"h":74},
	"pivot": {"x":0.5,"y":0.5}
},
"fugu_fat_swimming06":
{
	"frame": {"x":1327,"y":1128,"w":85,"h":74},
	"rotated": true,
	"trimmed": false,
	"spriteSourceSize": {"x":0,"y":0,"w":85,"h":74},
	"sourceSize": {"w":85,"h":74},
	"pivot": {"x":0.5,"y":0.5}
},
"fugu_fat_swimming07":
{
	"frame": {"x":1327,"y":1215,"w":85,"h":74},
	"rotated": true,
	"trimmed": false,
	"spriteSourceSize": {"x":0,"y":0,"w":85,"h":74},
	"sourceSize": {"w":85,"h":74},
	"pivot": {"x":0.5,"y":0.5}
},
"fugu_fat_swimming08":
{
	"frame": {"x":1718,"y":1443,"w":85,"h":74},
	"rotated": true,
	"trimmed": false,
	"spriteSourceSize": {"x":0,"y":0,"w":85,"h":74},
	"sourceSize": {"w":85,"h":74},
	"pivot": {"x":0.5,"y":0.5}
},
"fugu_fat_swimming09":
{
	"frame": {"x":1718,"y":1617,"w":84,"h":74},
	"rotated": true,
	"trimmed": true,
	"spriteSourceSize": {"x":1,"y":0,"w":84,"h":74},
	"sourceSize": {"w":85,"h":74},
	"pivot": {"x":0.5,"y":0.5}
},
"fugu_fat_swimming10":
{
	"frame": {"x":1718,"y":1530,"w":85,"h":74},
	"rotated": true,
	"trimmed": false,
	"spriteSourceSize": {"x":0,"y":0,"w":85,"h":74},
	"sourceSize": {"w":85,"h":74},
	"pivot": {"x":0.5,"y":0.5}
},
"fugu_thin_swimming01":
{
	"frame": {"x":850,"y":652,"w":36,"h":30},
	"rotated": false,
	"trimmed": false,
	"spriteSourceSize": {"x":0,"y":0,"w":36,"h":30},
	"sourceSize": {"w":36,"h":30},
	"pivot": {"x":0.535088,"y":0.234043}
},
"fugu_thin_swimming02":
{
	"frame": {"x":504,"y":742,"w":36,"h":30},
	"rotated": true,
	"trimmed": false,
	"spriteSourceSize": {"x":0,"y":0,"w":36,"h":30},
	"sourceSize": {"w":36,"h":30},
	"pivot": {"x":0.535088,"y":0.234043}
},
"fugu_thin_swimming03":
{
	"frame": {"x":850,"y":684,"w":36,"h":30},
	"rotated": false,
	"trimmed": false,
	"spriteSourceSize": {"x":0,"y":0,"w":36,"h":30},
	"sourceSize": {"w":36,"h":30},
	"pivot": {"x":0.535088,"y":0.234043}
},
"fugu_thin_swimming04":
{
	"frame": {"x":850,"y":716,"w":36,"h":30},
	"rotated": false,
	"trimmed": false,
	"spriteSourceSize": {"x":0,"y":0,"w":36,"h":30},
	"sourceSize": {"w":36,"h":30},
	"pivot": {"x":0.535088,"y":0.234043}
},
"fugu_thin_swimming05":
{
	"frame": {"x":850,"y":748,"w":36,"h":30},
	"rotated": false,
	"trimmed": false,
	"spriteSourceSize": {"x":0,"y":0,"w":36,"h":30},
	"sourceSize": {"w":36,"h":30},
	"pivot": {"x":0.535088,"y":0.234043}
},
"fugu_thin_swimming06":
{
	"frame": {"x":504,"y":780,"w":36,"h":30},
	"rotated": true,
	"trimmed": false,
	"spriteSourceSize": {"x":0,"y":0,"w":36,"h":30},
	"sourceSize": {"w":36,"h":30},
	"pivot": {"x":0.535088,"y":0.234043}
},
"fugu_thin_swimming07":
{
	"frame": {"x":504,"y":818,"w":36,"h":30},
	"rotated": true,
	"trimmed": false,
	"spriteSourceSize": {"x":0,"y":0,"w":36,"h":30},
	"sourceSize": {"w":36,"h":30},
	"pivot": {"x":0.535088,"y":0.234043}
},
"fugu_thin_swimming08":
{
	"frame": {"x":489,"y":856,"w":36,"h":30},
	"rotated": false,
	"trimmed": false,
	"spriteSourceSize": {"x":0,"y":0,"w":36,"h":30},
	"sourceSize": {"w":36,"h":30},
	"pivot": {"x":0.535088,"y":0.234043}
},
"fugu_thin_swimming09":
{
	"frame": {"x":489,"y":888,"w":36,"h":30},
	"rotated": false,
	"trimmed": false,
	"spriteSourceSize": {"x":0,"y":0,"w":36,"h":30},
	"sourceSize": {"w":36,"h":30},
	"pivot": {"x":0.535088,"y":0.234043}
},
"fugu_thin_swimming10":
{
	"frame": {"x":1376,"y":771,"w":36,"h":30},
	"rotated": true,
	"trimmed": false,
	"spriteSourceSize": {"x":0,"y":0,"w":36,"h":30},
	"sourceSize": {"w":36,"h":30},
	"pivot": {"x":0.535088,"y":0.234043}
},
"giant_clam01":
{
	"frame": {"x":789,"y":1460,"w":198,"h":92},
	"rotated": true,
	"trimmed": true,
	"spriteSourceSize": {"x":6,"y":106,"w":198,"h":92},
	"sourceSize": {"w":210,"h":198},
	"pivot": {"x":0.5,"y":0.5}
},
"giant_clam02":
{
	"frame": {"x":240,"y":1201,"w":210,"h":192},
	"rotated": false,
	"trimmed": true,
	"spriteSourceSize": {"x":0,"y":6,"w":210,"h":192},
	"sourceSize": {"w":210,"h":198},
	"pivot": {"x":0.5,"y":0.5}
},
"giant_clam03":
{
	"frame": {"x":1095,"y":1416,"w":210,"h":197},
	"rotated": false,
	"trimmed": true,
	"spriteSourceSize": {"x":0,"y":1,"w":210,"h":197},
	"sourceSize": {"w":210,"h":198},
	"pivot": {"x":0.5,"y":0.5}
},
"giant_clam04":
{
	"frame": {"x":1105,"y":1216,"w":210,"h":198},
	"rotated": false,
	"trimmed": false,
	"spriteSourceSize": {"x":0,"y":0,"w":210,"h":198},
	"sourceSize": {"w":210,"h":198},
	"pivot": {"x":0.5,"y":0.5}
},
"giant_clam05":
{
	"frame": {"x":1506,"y":1361,"w":210,"h":198},
	"rotated": false,
	"trimmed": false,
	"spriteSourceSize": {"x":0,"y":0,"w":210,"h":198},
	"sourceSize": {"w":210,"h":198},
	"pivot": {"x":0.5,"y":0.5}
},
"giant_clam06":
{
	"frame": {"x":883,"y":1300,"w":210,"h":198},
	"rotated": false,
	"trimmed": false,
	"spriteSourceSize": {"x":0,"y":0,"w":210,"h":198},
	"sourceSize": {"w":210,"h":198},
	"pivot": {"x":0.5,"y":0.5}
},
"giant_clam07":
{
	"frame": {"x":1307,"y":1507,"w":210,"h":197},
	"rotated": true,
	"trimmed": true,
	"spriteSourceSize": {"x":0,"y":1,"w":210,"h":197},
	"sourceSize": {"w":210,"h":198},
	"pivot": {"x":0.5,"y":0.5}
},
"giant_clam08":
{
	"frame": {"x":1842,"y":1,"w":205,"h":195},
	"rotated": false,
	"trimmed": true,
	"spriteSourceSize": {"x":2,"y":3,"w":205,"h":195},
	"sourceSize": {"w":210,"h":198},
	"pivot": {"x":0.5,"y":0.5}
},
"giant_clam09":
{
	"frame": {"x":452,"y":1239,"w":197,"h":125},
	"rotated": true,
	"trimmed": true,
	"spriteSourceSize": {"x":6,"y":73,"w":197,"h":125},
	"sourceSize": {"w":210,"h":198},
	"pivot": {"x":0.5,"y":0.5}
},
"giant_clam10":
{
	"frame": {"x":1,"y":1354,"w":196,"h":92},
	"rotated": false,
	"trimmed": true,
	"spriteSourceSize": {"x":6,"y":106,"w":196,"h":92},
	"sourceSize": {"w":210,"h":198},
	"pivot": {"x":0.5,"y":0.5}
},
"giant_clam11":
{
	"frame": {"x":1798,"y":1246,"w":196,"h":92},
	"rotated": false,
	"trimmed": true,
	"spriteSourceSize": {"x":6,"y":106,"w":196,"h":92},
	"sourceSize": {"w":210,"h":198},
	"pivot": {"x":0.5,"y":0.5}
},
"jellyfish_animation0001":
{
	"frame": {"x":1506,"y":1561,"w":52,"h":123},
	"rotated": true,
	"trimmed": true,
	"spriteSourceSize": {"x":0,"y":0,"w":52,"h":123},
	"sourceSize": {"w":53,"h":123},
	"pivot": {"x":0.5,"y":0.5}
},
"jellyfish_animation0002":
{
	"frame": {"x":1506,"y":1615,"w":52,"h":121},
	"rotated": true,
	"trimmed": true,
	"spriteSourceSize": {"x":0,"y":1,"w":52,"h":121},
	"sourceSize": {"w":53,"h":123},
	"pivot": {"x":0.5,"y":0.5}
},
"jellyfish_animation0003":
{
	"frame": {"x":536,"y":655,"w":53,"h":116},
	"rotated": false,
	"trimmed": true,
	"spriteSourceSize": {"x":0,"y":3,"w":53,"h":116},
	"sourceSize": {"w":53,"h":123},
	"pivot": {"x":0.5,"y":0.5}
},
"jellyfish_animation0004":
{
	"frame": {"x":833,"y":780,"w":53,"h":112},
	"rotated": false,
	"trimmed": true,
	"spriteSourceSize": {"x":0,"y":5,"w":53,"h":112},
	"sourceSize": {"w":53,"h":123},
	"pivot": {"x":0.5,"y":0.5}
},
"jellyfish_animation0005":
{
	"frame": {"x":1746,"y":688,"w":53,"h":110},
	"rotated": false,
	"trimmed": true,
	"spriteSourceSize": {"x":0,"y":6,"w":53,"h":110},
	"sourceSize": {"w":53,"h":123},
	"pivot": {"x":0.5,"y":0.5}
},
"jellyfish_animation0006":
{
	"frame": {"x":1744,"y":912,"w":53,"h":107},
	"rotated": false,
	"trimmed": true,
	"spriteSourceSize": {"x":0,"y":7,"w":53,"h":107},
	"sourceSize": {"w":53,"h":123},
	"pivot": {"x":0.5,"y":0.5}
},
"jellyfish_animation0007":
{
	"frame": {"x":1,"y":1660,"w":53,"h":105},
	"rotated": true,
	"trimmed": true,
	"spriteSourceSize": {"x":0,"y":7,"w":53,"h":105},
	"sourceSize": {"w":53,"h":123},
	"pivot": {"x":0.5,"y":0.5}
},
"jellyfish_animation0008":
{
	"frame": {"x":108,"y":1660,"w":53,"h":104},
	"rotated": true,
	"trimmed": true,
	"spriteSourceSize": {"x":0,"y":7,"w":53,"h":104},
	"sourceSize": {"w":53,"h":123},
	"pivot": {"x":0.5,"y":0.5}
},
"jellyfish_animation0009":
{
	"frame": {"x":832,"y":894,"w":53,"h":106},
	"rotated": false,
	"trimmed": true,
	"spriteSourceSize": {"x":0,"y":6,"w":53,"h":106},
	"sourceSize": {"w":53,"h":123},
	"pivot": {"x":0.5,"y":0.5}
},
"jellyfish_animation0010":
{
	"frame": {"x":1350,"y":814,"w":53,"h":107},
	"rotated": false,
	"trimmed": true,
	"spriteSourceSize": {"x":0,"y":5,"w":53,"h":107},
	"sourceSize": {"w":53,"h":123},
	"pivot": {"x":0.5,"y":0.5}
},
"jellyfish_animation0011":
{
	"frame": {"x":1746,"y":800,"w":53,"h":110},
	"rotated": false,
	"trimmed": true,
	"spriteSourceSize": {"x":0,"y":4,"w":53,"h":110},
	"sourceSize": {"w":53,"h":123},
	"pivot": {"x":0.5,"y":0.5}
},
"jellyfish_animation0012":
{
	"frame": {"x":536,"y":773,"w":53,"h":114},
	"rotated": false,
	"trimmed": true,
	"spriteSourceSize": {"x":0,"y":2,"w":53,"h":114},
	"sourceSize": {"w":53,"h":123},
	"pivot": {"x":0.5,"y":0.5}
},
"jellyfish_animation0013":
{
	"frame": {"x":1914,"y":1741,"w":52,"h":117},
	"rotated": true,
	"trimmed": true,
	"spriteSourceSize": {"x":0,"y":1,"w":52,"h":117},
	"sourceSize": {"w":53,"h":123},
	"pivot": {"x":0.5,"y":0.5}
},
"jellyfish_animation0014":
{
	"frame": {"x":1506,"y":1669,"w":52,"h":121},
	"rotated": true,
	"trimmed": true,
	"spriteSourceSize": {"x":0,"y":0,"w":52,"h":121},
	"sourceSize": {"w":53,"h":123},
	"pivot": {"x":0.5,"y":0.5}
},
"jellyfish_animation0015":
{
	"frame": {"x":1506,"y":1561,"w":52,"h":123},
	"rotated": true,
	"trimmed": true,
	"spriteSourceSize": {"x":0,"y":0,"w":52,"h":123},
	"sourceSize": {"w":53,"h":123},
	"pivot": {"x":0.5,"y":0.5}
},
"shark_animation01":
{
	"frame": {"x":934,"y":140,"w":300,"h":135},
	"rotated": false,
	"trimmed": true,
	"spriteSourceSize": {"x":0,"y":0,"w":300,"h":135},
	"sourceSize": {"w":300,"h":136},
	"pivot": {"x":0.5,"y":0.5}
},
"shark_animation02":
{
	"frame": {"x":1238,"y":1,"w":300,"h":136},
	"rotated": false,
	"trimmed": false,
	"spriteSourceSize": {"x":0,"y":0,"w":300,"h":136},
	"sourceSize": {"w":300,"h":136},
	"pivot": {"x":0.5,"y":0.5}
},
"shark_animation03":
{
	"frame": {"x":1540,"y":1,"w":300,"h":136},
	"rotated": false,
	"trimmed": false,
	"spriteSourceSize": {"x":0,"y":0,"w":300,"h":136},
	"sourceSize": {"w":300,"h":136},
	"pivot": {"x":0.5,"y":0.5}
},
"shark_animation04":
{
	"frame": {"x":625,"y":149,"w":299,"h":136},
	"rotated": false,
	"trimmed": true,
	"spriteSourceSize": {"x":0,"y":0,"w":299,"h":136},
	"sourceSize": {"w":300,"h":136},
	"pivot": {"x":0.5,"y":0.5}
},
"shark_animation05":
{
	"frame": {"x":1,"y":158,"w":298,"h":136},
	"rotated": false,
	"trimmed": true,
	"spriteSourceSize": {"x":0,"y":0,"w":298,"h":136},
	"sourceSize": {"w":300,"h":136},
	"pivot": {"x":0.5,"y":0.5}
},
"shark_animation06":
{
	"frame": {"x":301,"y":292,"w":297,"h":136},
	"rotated": false,
	"trimmed": true,
	"spriteSourceSize": {"x":0,"y":0,"w":297,"h":136},
	"sourceSize": {"w":300,"h":136},
	"pivot": {"x":0.5,"y":0.5}
},
"shark_animation07":
{
	"frame": {"x":1226,"y":277,"w":296,"h":136},
	"rotated": false,
	"trimmed": true,
	"spriteSourceSize": {"x":0,"y":0,"w":296,"h":136},
	"sourceSize": {"w":300,"h":136},
	"pivot": {"x":0.5,"y":0.5}
},
"shark_animation08":
{
	"frame": {"x":1524,"y":414,"w":295,"h":135},
	"rotated": false,
	"trimmed": true,
	"spriteSourceSize": {"x":0,"y":1,"w":295,"h":135},
	"sourceSize": {"w":300,"h":136},
	"pivot": {"x":0.5,"y":0.5}
},
"shark_animation09":
{
	"frame": {"x":1211,"y":415,"w":294,"h":135},
	"rotated": false,
	"trimmed": true,
	"spriteSourceSize": {"x":0,"y":1,"w":294,"h":135},
	"sourceSize": {"w":300,"h":136},
	"pivot": {"x":0.5,"y":0.5}
},
"shark_animation10":
{
	"frame": {"x":600,"y":425,"w":293,"h":134},
	"rotated": false,
	"trimmed": true,
	"spriteSourceSize": {"x":0,"y":2,"w":293,"h":134},
	"sourceSize": {"w":300,"h":136},
	"pivot": {"x":0.5,"y":0.5}
},
"shark_animation11":
{
	"frame": {"x":1507,"y":551,"w":294,"h":135},
	"rotated": false,
	"trimmed": true,
	"spriteSourceSize": {"x":0,"y":1,"w":294,"h":135},
	"sourceSize": {"w":300,"h":136},
	"pivot": {"x":0.5,"y":0.5}
},
"shark_animation12":
{
	"frame": {"x":914,"y":415,"w":295,"h":135},
	"rotated": false,
	"trimmed": true,
	"spriteSourceSize": {"x":0,"y":1,"w":295,"h":135},
	"sourceSize": {"w":300,"h":136},
	"pivot": {"x":0.5,"y":0.5}
},
"shark_animation13":
{
	"frame": {"x":1524,"y":277,"w":296,"h":135},
	"rotated": false,
	"trimmed": true,
	"spriteSourceSize": {"x":0,"y":1,"w":296,"h":135},
	"sourceSize": {"w":300,"h":136},
	"pivot": {"x":0.5,"y":0.5}
},
"shark_animation14":
{
	"frame": {"x":1,"y":296,"w":297,"h":136},
	"rotated": false,
	"trimmed": true,
	"spriteSourceSize": {"x":0,"y":0,"w":297,"h":136},
	"sourceSize": {"w":300,"h":136},
	"pivot": {"x":0.5,"y":0.5}
},
"shark_animation15":
{
	"frame": {"x":926,"y":277,"w":298,"h":136},
	"rotated": false,
	"trimmed": true,
	"spriteSourceSize": {"x":0,"y":0,"w":298,"h":136},
	"sourceSize": {"w":300,"h":136},
	"pivot": {"x":0.5,"y":0.5}
},
"shark_animation16":
{
	"frame": {"x":614,"y":287,"w":298,"h":136},
	"rotated": false,
	"trimmed": true,
	"spriteSourceSize": {"x":0,"y":0,"w":298,"h":136},
	"sourceSize": {"w":300,"h":136},
	"pivot": {"x":0.5,"y":0.5}
},
"shark_animation17":
{
	"frame": {"x":313,"y":154,"w":299,"h":136},
	"rotated": false,
	"trimmed": true,
	"spriteSourceSize": {"x":0,"y":0,"w":299,"h":136},
	"sourceSize": {"w":300,"h":136},
	"pivot": {"x":0.5,"y":0.5}
},
"shark_animation18":
{
	"frame": {"x":1238,"y":139,"w":300,"h":136},
	"rotated": false,
	"trimmed": false,
	"spriteSourceSize": {"x":0,"y":0,"w":300,"h":136},
	"sourceSize": {"w":300,"h":136},
	"pivot": {"x":0.5,"y":0.5}
},
"shark_animation19":
{
	"frame": {"x":1540,"y":139,"w":300,"h":136},
	"rotated": false,
	"trimmed": false,
	"spriteSourceSize": {"x":0,"y":0,"w":300,"h":136},
	"sourceSize": {"w":300,"h":136},
	"pivot": {"x":0.5,"y":0.5}
},
"shark_animation20":
{
	"frame": {"x":934,"y":140,"w":300,"h":135},
	"rotated": false,
	"trimmed": true,
	"spriteSourceSize": {"x":0,"y":0,"w":300,"h":135},
	"sourceSize": {"w":300,"h":136},
	"pivot": {"x":0.5,"y":0.5}
},
"shark_bite01":
{
	"frame": {"x":934,"y":1,"w":302,"h":137},
	"rotated": false,
	"trimmed": true,
	"spriteSourceSize": {"x":2,"y":13,"w":302,"h":137},
	"sourceSize": {"w":310,"h":155},
	"pivot": {"x":0.5,"y":0.5}
},
"shark_bite02":
{
	"frame": {"x":625,"y":1,"w":307,"h":146},
	"rotated": false,
	"trimmed": true,
	"spriteSourceSize": {"x":0,"y":8,"w":307,"h":146},
	"sourceSize": {"w":310,"h":155},
	"pivot": {"x":0.5,"y":0.5}
},
"shark_bite03":
{
	"frame": {"x":313,"y":1,"w":310,"h":151},
	"rotated": false,
	"trimmed": true,
	"spriteSourceSize": {"x":0,"y":4,"w":310,"h":151},
	"sourceSize": {"w":310,"h":155},
	"pivot": {"x":0.5,"y":0.5}
},
"shark_bite04":
{
	"frame": {"x":1,"y":1,"w":310,"h":155},
	"rotated": false,
	"trimmed": false,
	"spriteSourceSize": {"x":0,"y":0,"w":310,"h":155},
	"sourceSize": {"w":310,"h":155},
	"pivot": {"x":0.5,"y":0.5}
},
"swordfish_aggro01":
{
	"frame": {"x":1165,"y":552,"w":244,"h":91},
	"rotated": false,
	"trimmed": true,
	"spriteSourceSize": {"x":34,"y":6,"w":244,"h":91},
	"sourceSize": {"w":312,"h":107},
	"pivot": {"x":0.5,"y":0.5}
},
"swordfish_aggro02":
{
	"frame": {"x":1165,"y":645,"w":244,"h":91},
	"rotated": false,
	"trimmed": true,
	"spriteSourceSize": {"x":34,"y":6,"w":244,"h":91},
	"sourceSize": {"w":312,"h":107},
	"pivot": {"x":0.5,"y":0.5}
},
"swordfish_aggro03":
{
	"frame": {"x":888,"y":656,"w":244,"h":91},
	"rotated": false,
	"trimmed": true,
	"spriteSourceSize": {"x":34,"y":6,"w":244,"h":91},
	"sourceSize": {"w":312,"h":107},
	"pivot": {"x":0.5,"y":0.5}
},
"swordfish_aggro04":
{
	"frame": {"x":596,"y":561,"w":268,"h":89},
	"rotated": false,
	"trimmed": true,
	"spriteSourceSize": {"x":10,"y":7,"w":268,"h":89},
	"sourceSize": {"w":312,"h":107},
	"pivot": {"x":0.5,"y":0.5}
},
"swordfish_aggro05":
{
	"frame": {"x":1,"y":629,"w":274,"h":89},
	"rotated": false,
	"trimmed": true,
	"spriteSourceSize": {"x":4,"y":7,"w":274,"h":89},
	"sourceSize": {"w":312,"h":107},
	"pivot": {"x":0.5,"y":0.5}
},
"swordfish_aggro06":
{
	"frame": {"x":1,"y":538,"w":275,"h":89},
	"rotated": false,
	"trimmed": true,
	"spriteSourceSize": {"x":3,"y":7,"w":275,"h":89},
	"sourceSize": {"w":312,"h":107},
	"pivot": {"x":0.5,"y":0.5}
},
"swordfish_aggro07":
{
	"frame": {"x":1,"y":434,"w":275,"h":102},
	"rotated": false,
	"trimmed": true,
	"spriteSourceSize": {"x":3,"y":1,"w":275,"h":102},
	"sourceSize": {"w":312,"h":107},
	"pivot": {"x":0.5,"y":0.5}
},
"swordfish_aggro08":
{
	"frame": {"x":278,"y":534,"w":275,"h":102},
	"rotated": false,
	"trimmed": true,
	"spriteSourceSize": {"x":3,"y":1,"w":275,"h":102},
	"sourceSize": {"w":312,"h":107},
	"pivot": {"x":0.5,"y":0.5}
},
"swordfish_aggro09":
{
	"frame": {"x":1,"y":720,"w":255,"h":102},
	"rotated": false,
	"trimmed": true,
	"spriteSourceSize": {"x":23,"y":1,"w":255,"h":102},
	"sourceSize": {"w":312,"h":107},
	"pivot": {"x":0.5,"y":0.5}
},
"swordfish_aggro10":
{
	"frame": {"x":277,"y":638,"w":257,"h":102},
	"rotated": false,
	"trimmed": true,
	"spriteSourceSize": {"x":21,"y":1,"w":257,"h":102},
	"sourceSize": {"w":312,"h":107},
	"pivot": {"x":0.5,"y":0.5}
},
"swordfish_aggro11":
{
	"frame": {"x":593,"y":652,"w":255,"h":102},
	"rotated": false,
	"trimmed": true,
	"spriteSourceSize": {"x":23,"y":1,"w":255,"h":102},
	"sourceSize": {"w":312,"h":107},
	"pivot": {"x":0.5,"y":0.5}
},
"swordfish_aggro12":
{
	"frame": {"x":1803,"y":589,"w":244,"h":102},
	"rotated": false,
	"trimmed": true,
	"spriteSourceSize": {"x":34,"y":1,"w":244,"h":102},
	"sourceSize": {"w":312,"h":107},
	"pivot": {"x":0.5,"y":0.5}
},
"swordfish_aggro13":
{
	"frame": {"x":258,"y":742,"w":244,"h":102},
	"rotated": false,
	"trimmed": true,
	"spriteSourceSize": {"x":34,"y":1,"w":244,"h":102},
	"sourceSize": {"w":312,"h":107},
	"pivot": {"x":0.5,"y":0.5}
},
"swordfish_aggro14":
{
	"frame": {"x":1,"y":824,"w":244,"h":102},
	"rotated": false,
	"trimmed": true,
	"spriteSourceSize": {"x":34,"y":1,"w":244,"h":102},
	"sourceSize": {"w":312,"h":107},
	"pivot": {"x":0.5,"y":0.5}
},
"swordfish_aggro15":
{
	"frame": {"x":895,"y":552,"w":268,"h":102},
	"rotated": false,
	"trimmed": true,
	"spriteSourceSize": {"x":10,"y":1,"w":268,"h":102},
	"sourceSize": {"w":312,"h":107},
	"pivot": {"x":0.5,"y":0.5}
},
"swordfish_aggro16":
{
	"frame": {"x":300,"y":430,"w":278,"h":102},
	"rotated": false,
	"trimmed": true,
	"spriteSourceSize": {"x":0,"y":1,"w":278,"h":102},
	"sourceSize": {"w":312,"h":107},
	"pivot": {"x":0.5,"y":0.5}
},
"swordfish_animation01":
{
	"frame": {"x":1822,"y":383,"w":218,"h":101},
	"rotated": false,
	"trimmed": true,
	"spriteSourceSize": {"x":41,"y":2,"w":218,"h":101},
	"sourceSize": {"w":312,"h":107},
	"pivot": {"x":0.5,"y":0.5}
},
"swordfish_animation02":
{
	"frame": {"x":1821,"y":486,"w":218,"h":101},
	"rotated": false,
	"trimmed": true,
	"spriteSourceSize": {"x":41,"y":2,"w":218,"h":101},
	"sourceSize": {"w":312,"h":107},
	"pivot": {"x":0.5,"y":0.5}
},
"swordfish_animation03":
{
	"frame": {"x":1507,"y":949,"w":218,"h":101},
	"rotated": false,
	"trimmed": true,
	"spriteSourceSize": {"x":41,"y":2,"w":218,"h":101},
	"sourceSize": {"w":312,"h":107},
	"pivot": {"x":0.5,"y":0.5}
},
"swordfish_animation04":
{
	"frame": {"x":489,"y":920,"w":218,"h":100},
	"rotated": true,
	"trimmed": true,
	"spriteSourceSize": {"x":41,"y":2,"w":218,"h":100},
	"sourceSize": {"w":312,"h":107},
	"pivot": {"x":0.5,"y":0.5}
},
"swordfish_animation05":
{
	"frame": {"x":888,"y":825,"w":218,"h":99},
	"rotated": false,
	"trimmed": true,
	"spriteSourceSize": {"x":41,"y":3,"w":218,"h":99},
	"sourceSize": {"w":312,"h":107},
	"pivot": {"x":0.5,"y":0.5}
},
"swordfish_animation06":
{
	"frame": {"x":591,"y":985,"w":218,"h":99},
	"rotated": false,
	"trimmed": true,
	"spriteSourceSize": {"x":41,"y":3,"w":218,"h":99},
	"sourceSize": {"w":312,"h":107},
	"pivot": {"x":0.5,"y":0.5}
},
"swordfish_animation07":
{
	"frame": {"x":1407,"y":992,"w":218,"h":98},
	"rotated": true,
	"trimmed": true,
	"spriteSourceSize": {"x":41,"y":3,"w":218,"h":98},
	"sourceSize": {"w":312,"h":107},
	"pivot": {"x":0.5,"y":0.5}
},
"swordfish_animation08":
{
	"frame": {"x":887,"y":926,"w":218,"h":98},
	"rotated": false,
	"trimmed": true,
	"spriteSourceSize": {"x":41,"y":3,"w":218,"h":98},
	"sourceSize": {"w":312,"h":107},
	"pivot": {"x":0.5,"y":0.5}
},
"swordfish_animation09":
{
	"frame": {"x":1408,"y":772,"w":218,"h":97},
	"rotated": true,
	"trimmed": true,
	"spriteSourceSize": {"x":41,"y":4,"w":218,"h":97},
	"sourceSize": {"w":312,"h":107},
	"pivot": {"x":0.5,"y":0.5}
},
"swordfish_animation10":
{
	"frame": {"x":887,"y":1026,"w":218,"h":97},
	"rotated": false,
	"trimmed": true,
	"spriteSourceSize": {"x":41,"y":4,"w":218,"h":97},
	"sourceSize": {"w":312,"h":107},
	"pivot": {"x":0.5,"y":0.5}
},
"swordfish_animation11":
{
	"frame": {"x":1107,"y":1117,"w":218,"h":97},
	"rotated": false,
	"trimmed": true,
	"spriteSourceSize": {"x":41,"y":4,"w":218,"h":97},
	"sourceSize": {"w":312,"h":107},
	"pivot": {"x":0.5,"y":0.5}
},
"swordfish_animation12":
{
	"frame": {"x":591,"y":1086,"w":218,"h":98},
	"rotated": false,
	"trimmed": true,
	"spriteSourceSize": {"x":41,"y":3,"w":218,"h":98},
	"sourceSize": {"w":312,"h":107},
	"pivot": {"x":0.5,"y":0.5}
},
"swordfish_animation13":
{
	"frame": {"x":1107,"y":1017,"w":218,"h":98},
	"rotated": false,
	"trimmed": true,
	"spriteSourceSize": {"x":41,"y":3,"w":218,"h":98},
	"sourceSize": {"w":312,"h":107},
	"pivot": {"x":0.5,"y":0.5}
},
"swordfish_animation14":
{
	"frame": {"x":1108,"y":916,"w":218,"h":99},
	"rotated": false,
	"trimmed": true,
	"spriteSourceSize": {"x":41,"y":3,"w":218,"h":99},
	"sourceSize": {"w":312,"h":107},
	"pivot": {"x":0.5,"y":0.5}
},
"swordfish_animation15":
{
	"frame": {"x":1507,"y":1052,"w":218,"h":99},
	"rotated": false,
	"trimmed": true,
	"spriteSourceSize": {"x":41,"y":3,"w":218,"h":99},
	"sourceSize": {"w":312,"h":107},
	"pivot": {"x":0.5,"y":0.5}
},
"swordfish_animation16":
{
	"frame": {"x":1507,"y":1153,"w":218,"h":99},
	"rotated": false,
	"trimmed": true,
	"spriteSourceSize": {"x":41,"y":3,"w":218,"h":99},
	"sourceSize": {"w":312,"h":107},
	"pivot": {"x":0.5,"y":0.5}
},
"swordfish_animation17":
{
	"frame": {"x":1130,"y":814,"w":218,"h":100},
	"rotated": false,
	"trimmed": true,
	"spriteSourceSize": {"x":41,"y":2,"w":218,"h":100},
	"sourceSize": {"w":312,"h":107},
	"pivot": {"x":0.5,"y":0.5}
},
"swordfish_animation18":
{
	"frame": {"x":1799,"y":937,"w":218,"h":101},
	"rotated": false,
	"trimmed": true,
	"spriteSourceSize": {"x":41,"y":2,"w":218,"h":101},
	"sourceSize": {"w":312,"h":107},
	"pivot": {"x":0.5,"y":0.5}
},
"swordfish_animation19":
{
	"frame": {"x":1798,"y":1040,"w":218,"h":101},
	"rotated": false,
	"trimmed": true,
	"spriteSourceSize": {"x":41,"y":2,"w":218,"h":101},
	"sourceSize": {"w":312,"h":107},
	"pivot": {"x":0.5,"y":0.5}
},
"swordfish_transition01":
{
	"frame": {"x":1798,"y":1143,"w":218,"h":101},
	"rotated": false,
	"trimmed": true,
	"spriteSourceSize": {"x":41,"y":2,"w":218,"h":101},
	"sourceSize": {"w":312,"h":107},
	"pivot": {"x":0.5,"y":0.5}
},
"swordfish_transition02":
{
	"frame": {"x":887,"y":1195,"w":216,"h":103},
	"rotated": false,
	"trimmed": true,
	"spriteSourceSize": {"x":41,"y":1,"w":216,"h":103},
	"sourceSize": {"w":312,"h":107},
	"pivot": {"x":0.5,"y":0.5}
},
"swordfish_transition03":
{
	"frame": {"x":591,"y":1186,"w":214,"h":104},
	"rotated": false,
	"trimmed": true,
	"spriteSourceSize": {"x":41,"y":0,"w":214,"h":104},
	"sourceSize": {"w":312,"h":107},
	"pivot": {"x":0.5,"y":0.5}
},
"swordfish_transition04":
{
	"frame": {"x":1507,"y":1254,"w":212,"h":105},
	"rotated": false,
	"trimmed": true,
	"spriteSourceSize": {"x":41,"y":0,"w":212,"h":105},
	"sourceSize": {"w":312,"h":107},
	"pivot": {"x":0.5,"y":0.5}
},
"swordfish_transition05":
{
	"frame": {"x":579,"y":1292,"w":210,"h":105},
	"rotated": false,
	"trimmed": true,
	"spriteSourceSize": {"x":41,"y":0,"w":210,"h":105},
	"sourceSize": {"w":312,"h":107},
	"pivot": {"x":0.5,"y":0.5}
},
"swordfish_transition06":
{
	"frame": {"x":579,"y":1399,"w":208,"h":105},
	"rotated": false,
	"trimmed": true,
	"spriteSourceSize": {"x":41,"y":0,"w":208,"h":105},
	"sourceSize": {"w":312,"h":107},
	"pivot": {"x":0.5,"y":0.5}
},
"swordfish_transition07":
{
	"frame": {"x":883,"y":1500,"w":206,"h":106},
	"rotated": false,
	"trimmed": true,
	"spriteSourceSize": {"x":41,"y":0,"w":206,"h":106},
	"sourceSize": {"w":312,"h":107},
	"pivot": {"x":0.5,"y":0.5}
},
"swordfish_transition08":
{
	"frame": {"x":1842,"y":198,"w":204,"h":106},
	"rotated": false,
	"trimmed": true,
	"spriteSourceSize": {"x":41,"y":0,"w":204,"h":106},
	"sourceSize": {"w":312,"h":107},
	"pivot": {"x":0.5,"y":0.5}
},
"swordfish_transition09":
{
	"frame": {"x":883,"y":1608,"w":202,"h":107},
	"rotated": false,
	"trimmed": true,
	"spriteSourceSize": {"x":41,"y":0,"w":202,"h":107},
	"sourceSize": {"w":312,"h":107},
	"pivot": {"x":0.5,"y":0.5}
},
"swordfish_transition10":
{
	"frame": {"x":1087,"y":1684,"w":199,"h":107},
	"rotated": false,
	"trimmed": true,
	"spriteSourceSize": {"x":42,"y":0,"w":199,"h":107},
	"sourceSize": {"w":312,"h":107},
	"pivot": {"x":0.5,"y":0.5}
},
"tiger_shark01":
{
	"frame": {"x":1794,"y":1502,"w":141,"h":165},
	"rotated": true,
	"trimmed": true,
	"spriteSourceSize": {"x":62,"y":2,"w":141,"h":165},
	"sourceSize": {"w":240,"h":167},
	"pivot": {"x":0.5,"y":0.5}
},
"tiger_shark02":
{
	"frame": {"x":1798,"y":1340,"w":165,"h":160},
	"rotated": false,
	"trimmed": true,
	"spriteSourceSize": {"x":27,"y":5,"w":165,"h":160},
	"sourceSize": {"w":240,"h":167},
	"pivot": {"x":0.5,"y":0.5}
},
"tiger_shark03":
{
	"frame": {"x":1,"y":1207,"w":197,"h":145},
	"rotated": false,
	"trimmed": true,
	"spriteSourceSize": {"x":11,"y":9,"w":197,"h":145},
	"sourceSize": {"w":240,"h":167},
	"pivot": {"x":0.5,"y":0.5}
},
"tiger_shark04":
{
	"frame": {"x":591,"y":832,"w":239,"h":151},
	"rotated": false,
	"trimmed": true,
	"spriteSourceSize": {"x":0,"y":0,"w":239,"h":151},
	"sourceSize": {"w":240,"h":167},
	"pivot": {"x":0.5,"y":0.5}
},
"urchin01":
{
	"frame": {"x":1376,"y":738,"w":31,"h":31},
	"rotated": false,
	"trimmed": true,
	"spriteSourceSize": {"x":28,"y":26,"w":31,"h":31},
	"sourceSize": {"w":82,"h":83},
	"pivot": {"x":0.5,"y":0.5}
},
"urchin02":
{
	"frame": {"x":555,"y":618,"w":36,"h":35},
	"rotated": false,
	"trimmed": true,
	"spriteSourceSize": {"x":26,"y":24,"w":36,"h":35},
	"sourceSize": {"w":82,"h":83},
	"pivot": {"x":0.5,"y":0.5}
},
"urchin03":
{
	"frame": {"x":1307,"y":1454,"w":51,"h":51},
	"rotated": false,
	"trimmed": true,
	"spriteSourceSize": {"x":17,"y":16,"w":51,"h":51},
	"sourceSize": {"w":82,"h":83},
	"pivot": {"x":0.5,"y":0.5}
},
"urchin04":
{
	"frame": {"x":1,"y":1717,"w":68,"h":67},
	"rotated": true,
	"trimmed": true,
	"spriteSourceSize": {"x":8,"y":8,"w":68,"h":67},
	"sourceSize": {"w":82,"h":83},
	"pivot": {"x":0.5,"y":0.5}
},
"urchin05":
{
	"frame": {"x":505,"y":1761,"w":82,"h":83},
	"rotated": true,
	"trimmed": false,
	"spriteSourceSize": {"x":0,"y":0,"w":82,"h":83},
	"sourceSize": {"w":82,"h":83},
	"pivot": {"x":0.5,"y":0.5}
}},
"meta": {
	"app": "http://www.codeandweb.com/texturepacker",
	"version": "1.0",
	"image": "enemies@2x.png",
	"format": "RGBA8888",
	"size": {"w":2048,"h":2048},
	"scale": "0.32",
	"smartupdate": "$TexturePacker:SmartUpdate:9e57175426c54e09f3f99510df4e1275:3572f02bffecdf09ac8b274694a97eeb:92da8fb89bf3079a62e05bb41a9b467c$"
}
}
